{"__symbolic":"module","version":4,"metadata":{"ThreeModule":{"__symbolic":"class","decorators":[{"__symbolic":"call","expression":{"__symbolic":"reference","module":"@angular/core","name":"NgModule","line":9,"character":1},"arguments":[{"imports":[{"__symbolic":"reference","module":"@angular/common","name":"CommonModule","line":10,"character":12}],"declarations":[{"__symbolic":"reference","name":"ɵa"},{"__symbolic":"reference","name":"ɵb"}],"exports":[{"__symbolic":"reference","name":"ɵa"},{"__symbolic":"reference","name":"ɵb"}],"providers":[{"__symbolic":"reference","name":"ɵc"}]}]}],"members":{}}},"origins":{"ThreeModule":"./src/three.module","ɵa":"./src/components","ɵb":"./src/pipes","ɵc":"./src/services"},"importAs":"my-package/lib/module-three"}